JupyterPy/__init__.py
JupyterPy/core.py
JupyterPy-1.0.0.dist-info/METADATA
JupyterPy-1.0.0.dist-info/WHEEL
JupyterPy-1.0.0.dist-info/top_level.txt
JupyterPy-1.0.0.dist-info/RECORD
