Metadata-Version: 2.1
Name: JupyterPy
Version: 1.0.0
Summary: Automation API to convert Jupyter Notebook (.ipynb) JSON format into Python file (.py), with the capabilities to add magic functions to determine which cells to be exported.
Home-page: https://github.com/bengsoon/jupyterpy
Author: Bengsoon Chuah
Author-email: bengsoonchuah@gmail.com
License: MIT
Platform: UNKNOWN
Classifier: License :: OSI Approved :: MIT License
Classifier: Programming Language :: Python :: 3
Classifier: Programming Language :: Python :: 3.8
Requires-Dist: pathlib
Requires-Dist: regex
Requires-Dist: nbformat
